{
  "generado": "2026-07-08T17:07:29-05:00",
  "corte": 17,
  "corte_neto": 17,
  "fecha_hoy": "2026-07-08",
  "igv": 1.18,
  "marcas": {
    "TIENDAS EFE": {
      "hoy": {
        "venta_neta": 98975.67,
        "trx_netas": 192,
        "ticket_neto": 515.5
      },
      "por_dia": {
        "2026-07-06": {
          "venta_neta": 277877.12,
          "trx_netas": 340,
          "ticket_neto": 817.29
        },
        "2026-07-07": {
          "venta_neta": 190565.17,
          "trx_netas": 254,
          "ticket_neto": 750.26
        },
        "2026-07-08": {
          "venta_neta": 98975.67,
          "trx_netas": 192,
          "ticket_neto": 515.5
        }
      }
    },
    "LA CURACAO": {
      "hoy": {
        "venta_neta": 102397.71,
        "trx_netas": 171,
        "ticket_neto": 598.82
      },
      "por_dia": {
        "2026-07-06": {
          "venta_neta": 354922.5,
          "trx_netas": 458,
          "ticket_neto": 774.94
        },
        "2026-07-07": {
          "venta_neta": 202368.35,
          "trx_netas": 324,
          "ticket_neto": 624.59
        },
        "2026-07-08": {
          "venta_neta": 102397.71,
          "trx_netas": 171,
          "ticket_neto": 598.82
        }
      }
    }
  }
}